ngautonml/__init__.py
ngautonml/aggregators/__init__.py
ngautonml/aggregators/impl/__init__.py
ngautonml/aggregators/impl/aggregate_ranker.py
ngautonml/aggregators/impl/aggregator.py
ngautonml/aggregators/impl/aggregator_auto.py
ngautonml/aggregators/impl/aggregator_auto_test.py
ngautonml/aggregators/impl/aggregator_catalog.py
ngautonml/aggregators/impl/aggregator_test.py
ngautonml/aggregators/impl/test_aggregators.py
ngautonml/aggregators/impl/tsad/distributions/__init__.py
ngautonml/aggregators/impl/tsad/distributions/mallows_kendall.py
ngautonml/aggregators/impl/tsad/distributions/mallows_model.py
ngautonml/aggregators/impl/tsad/rank_aggregation.py
ngautonml/aggregators/test_aggregator_test.py
ngautonml/aggregators/test_aggregators.py
ngautonml/aggregators/tsad_aggregator.py
ngautonml/aggregators/tsad_aggregator_test.py
ngautonml/aggregators/tsad_aggregators.py
ngautonml/algorithms/__init__.py
ngautonml/algorithms/abstractor/__init__.py
ngautonml/algorithms/abstractor/impl/__init__.py
ngautonml/algorithms/abstractor/impl/abstractor.py
ngautonml/algorithms/abstractor/impl/abstractor_instance.py
ngautonml/algorithms/abstractor/impl/abstractor_test.py
ngautonml/algorithms/abstractor/share.py
ngautonml/algorithms/abstractor/share_test.py
ngautonml/algorithms/binarizer.py
ngautonml/algorithms/binarizer_test.py
ngautonml/algorithms/column_parser.py
ngautonml/algorithms/column_parser_test.py
ngautonml/algorithms/connect.py
ngautonml/algorithms/connect_test.py
ngautonml/algorithms/distributed/DistAIModel.py
ngautonml/algorithms/distributed/GMM.py
ngautonml/algorithms/distributed/__init__.py
ngautonml/algorithms/distributed/auton_decision_tree.py
ngautonml/algorithms/distributed/auton_decision_tree_neighbor.py
ngautonml/algorithms/distributed/auton_decision_tree_test.py
ngautonml/algorithms/distributed/auton_gaussian_mixture_models.py
ngautonml/algorithms/distributed/auton_gaussian_mixture_models_test.py
ngautonml/algorithms/distributed/auton_linear_regression.py
ngautonml-0.5.0b8.dist-info/LICENSE
ngautonml-0.5.0b8.dist-info/METADATA
ngautonml-0.5.0b8.dist-info/WHEEL
ngautonml-0.5.0b8.dist-info/entry_points.txt
ngautonml-0.5.0b8.dist-info/RECORD
