Metadata-Version: 2.3
Name: ngautonml
Version: 0.5.0b8
Summary: Automated Machine Learning Pipeline Generation
License: Apache-2.0
Keywords: machine learning
Author: L.H. Piggy Yarroll
Author-email: piggy@acm.org
Requires-Python: >=3.9,<4.0
Classifier: Development Status :: 4 - Beta
Classifier: Intended Audience :: Science/Research
Classifier: License :: OSI Approved :: Apache Software License
Classifier: Programming Language :: Python :: 3
Classifier: Programming Language :: Python :: 3.9
Classifier: Programming Language :: Python :: 3.10
Classifier: Programming Language :: Python :: 3.11
Classifier: Programming Language :: Python :: 3.12
Classifier: Programming Language :: Python :: 3.13
Classifier: Topic :: Scientific/Engineering :: Artificial Intelligence
Classifier: Typing :: Typed
Requires-Dist: aenum (==3.*)
Requires-Dist: autograd (==1.*)
Requires-Dist: build (==1.*)
Requires-Dist: cvxpy (==1.*)
Requires-Dist: flask (==3.*)
Requires-Dist: frozendict (==2.*)
Requires-Dist: kafka-python (==2.0.4)
Requires-Dist: mlflow (==2.*)
Requires-Dist: networkx (==3.*)
Requires-Dist: numpy (==1.*)
Requires-Dist: pandas (==2.*)
Requires-Dist: pytest (==7.*)
Requires-Dist: scikit-learn (>=1.2.2,<2.0.0)
Requires-Dist: tensorflow (==2.*)
Project-URL: Bug Tracker, http://gitlab.com/autonlab/ngautonml/issues
Project-URL: Documentation, https://autonlab.gitlab.io/ngautonml
Project-URL: Design, https://docs.google.com/document/d/1SaR-2WRy5kwHX-1BSh2yYHjif09a7xYcMxw4PStlpE8
Project-URL: Repository, https://gitlab.com/autonlab/ngautonml
